bento/__init__.py
bento/__main__.py
bento/base_context.py
bento/cli.py
bento/commands/__init__.py
bento/commands/archive.py
bento/commands/autocomplete.py
bento/commands/autorun.py
bento/commands/check.py
bento/commands/ci.py
bento/commands/disable.py
bento/commands/enable.py
bento/commands/init.py
bento/commands/register.py
bento/config.py
bento/configs/.bentoignore
bento/configs/default.yml
bento/configs/extra-ignore-patterns
bento/configs/gh-actions.yml
bento/configs/headless.yml
bento/configs/pre-commit.template
bento/configs/semgrep.yml
bento/constants.py
bento/content/__init__.py
bento/content/ci.py
bento/content/init.py
bento/content/register.py
bento/context.py
bento/decorators.py
bento/error.py
bento/extra/__init__.py
bento/extra/bandit.py
bento/extra/base_sgrep.py
bento/extra/boto3.py
bento/extra/click.py
bento/extra/dlint.py
bento/extra/eslint/.eslintrc-default.yml
bento/extra/eslint/.eslintrc-react-and-typescript.yml
bento/extra/eslint/.eslintrc-react.yml
bento/extra/eslint/.eslintrc-typescript.yml
bento/extra/eslint/package.json
bento/extra/eslint.py
bento/extra/flake8.py
bento/extra/flask.py
bento/extra/gosec.py
bento/extra/grep.md
bento/extra/grep.py
bento/extra/hadolint.py
bento/extra/jinjalint.py
bento/extra/pyre.py
bento/extra/r2c_check_registry.py
bento/extra/requests.py
bento/extra/sgrep.py
bento/extra/shellcheck.py
bento/fignore.py
bento/formatter/__init__.py
bento/formatter/base.py
bento/formatter/clippy.py
bento/formatter/histo.py
bento/formatter/json.py
bento/formatter/reporter.py
bento/formatter/stylish.py
bento/git.py
bento/metrics.py
bento/network.py
bento/orchestrator.py
bento/parser.py
bento/paths.py
bento/renderer.py
bento/result.py
bento/run_cache.py
bento/target_file_manager.py
bento/tool/__init__.py
bento/tool/output.py
bento/tool/runner/__init__.py
bento/tool/runner/docker.py
bento/tool/runner/js_tool.py
bento/tool/runner/python_tool.py
bento/tool/tool.py
bento/tool_runner.py
bento/util.py
bento/violation.py
bento_headless-0.11.2.dist-info/entry_points.txt
bento_headless-0.11.2.dist-info/LICENSE
bento_headless-0.11.2.dist-info/WHEEL
bento_headless-0.11.2.dist-info/METADATA
bento_headless-0.11.2.dist-info/RECORD
