Metadata-Version: 2.1
Name: bento-headless
Version: 0.11.2
Summary: Git-aware utility for automated program analysis
Home-page: http://bento.dev
License: Proprietary
Author: Return To Corporation
Author-email: hello@r2c.dev
Requires-Python: >=3.6,<4.0
Classifier: License :: Other/Proprietary License
Classifier: Operating System :: OS Independent
Classifier: Programming Language :: Python :: 3
Classifier: Programming Language :: Python :: 3.6
Classifier: Programming Language :: Python :: 3.7
Classifier: Programming Language :: Python :: 3.8
Requires-Dist: PyYAML (>=5.1.2)
Requires-Dist: attrs (>=18.2.0,<=19.3.0)
Requires-Dist: click (>=7.0,<8.0)
Requires-Dist: docker (>=3.7,<4.0)
Requires-Dist: frozendict (>=1.2,<2.0)
Requires-Dist: gitpython (>=2.1,<3.0)
Requires-Dist: packaging (>=14.0)
Requires-Dist: pre-commit (>=1.0.0,<=1.18.3)
Requires-Dist: psutil (>=5.6.3,<5.7.0)
Requires-Dist: pymmh3 (>=0.0.5,<0.1.0)
Requires-Dist: semantic-version (>=2.8.0,<2.9.0)
Requires-Dist: tqdm (>=4.36.1,<4.37.0)
Requires-Dist: validate-email (>=1.3,<2.0)
Project-URL: Bug Tracker, https://github.com/returntocorp/bento/issues
Project-URL: Blog, https://bento.dev/blog/
Project-URL: Code Checks, https://bento.dev/checks/
Project-URL: Source Code, https://github.com/returntocorp/bento
